libspitz/Args.py
libspitz/Blob.py
libspitz/ClientEndpoint.py
libspitz/Endpoint.py
libspitz/JobBinary.py
libspitz/Listener.py
libspitz/LogUtils.py
libspitz/PerfModule.py
libspitz/Pointer.py
libspitz/Result.py
libspitz/SimpleEndpoint.py
libspitz/TaskPool.py
libspitz/Timeout.py
libspitz/UIDUtils.py
libspitz/__init__.py
libspitz/memstat.py
libspitz/config/__init__.py
libspitz/messaging/MessagingError.py
libspitz/messaging/SocketClosed.py
libspitz/messaging/__init__.py
pypits-0.0.4.data/scripts/pypits-examples
pypits-0.0.4.data/scripts/pypits-gen-api
pypits-0.0.4.data/scripts/pypits-jm
pypits-0.0.4.data/scripts/pypits-run
pypits-0.0.4.data/scripts/pypits-tm
pypits-0.0.4.dist-info/LICENSE
pypits-0.0.4.dist-info/METADATA
pypits-0.0.4.dist-info/WHEEL
pypits-0.0.4.dist-info/top_level.txt
pypits-0.0.4.dist-info/RECORD
