Metadata-Version: 2.1
Name: pypits
Version: 0.0.4
Summary: The reference python implementation of the SPITS programming model
Home-page: https://github.com/hpg-cepetro/pypits
Author: Caian Benedicto
Author-email: caian@ggaunicamp.com
License: UNKNOWN
Platform: UNKNOWN
Classifier: Programming Language :: Python
Classifier: License :: OSI Approved :: MIT License
Classifier: Operating System :: OS Independent
Requires-Python: >=2.6
